Metadata-Version: 2.1
Name: fabada
Version: 0.1
Summary: Fully Adaptive Bayesian Algorithm for Data Analysis FABADA
Home-page: https://github.com/PabloMSanAla/fabada
Author: Pablo M. Sánchez Alarcón
Author-email: pablom.sanala@gmail.com
License: UNKNOWN
Download-URL: https://github.com/PabloMSanAla/fabada/archive/refs/tags/v_01.tar.gz
Project-URL: Bug Tracker, https://github.com/PabloMSanAla/fabada/issues
Keywords: Astronomy,Image Denoising,Bayesian
Platform: UNKNOWN
Classifier: Development Status :: 3 - Alpha
Classifier: License :: Free for non-commercial use
Classifier: Intended Audience :: Education
Classifier: Intended Audience :: Science/Research
Classifier: Operating System :: POSIX :: Linux
Classifier: Operating System :: Microsoft :: Windows
Classifier: Operating System :: MacOS
Classifier: Programming Language :: Python :: 3
Classifier: Topic :: Scientific/Engineering :: Information Analysis
Classifier: Topic :: Scientific/Engineering :: Mathematics
Classifier: Topic :: Software Development :: Libraries :: Python Modules
Requires-Python: >=3.5
